Orr_Sommerfeld_convmix_CGB/OS_CM.py
Orr_Sommerfeld_convmix_CGB/__init__.py
orr_sommerfeld_convmix_cgb-0.2.9.dist-info/METADATA
orr_sommerfeld_convmix_cgb-0.2.9.dist-info/WHEEL
orr_sommerfeld_convmix_cgb-0.2.9.dist-info/licenses/LICENSE
orr_sommerfeld_convmix_cgb-0.2.9.dist-info/RECORD
