Metadata-Version: 2.1
Name: Orr_Sommerfeld_convmix_CGB
Version: 0.2.9
Summary: Paquete para cálculo de autovalores y autofunciones.
Project-URL: Homepage, https://github.com/pypa/sampleproject
Project-URL: Bug Tracker, https://github.com/pypa/sampleproject/issues
Project-URL: Source Code, https://gitlab.com/mecom-cnea-os/orr-sommerfeld-convmix-cgb
Author-email: Pablo Szuban <pablo.szuban@ib.edu.ar>
License-File: LICENSE
Classifier: License :: OSI Approved :: MIT License
Classifier: Operating System :: OS Independent
Classifier: Programming Language :: Python :: 3
Requires-Python: >=3.7
